pycvextract/__init__.py
pycvextract/custom_train.py
pycvextract/meta.json
pycvextract/requirements.txt
pycvextract/reshelper.py
pycvextract/resume_parser.py
pycvextract/tokenizer
pycvextract/.vscode/settings.json
pycvextract/ner/cfg
pycvextract/ner/model
pycvextract/ner/moves
pycvextract/vocab/key2row
pycvextract/vocab/lexemes.bin
pycvextract/vocab/strings.json
pycvextract/vocab/vectors
pycvextract-0.0.1.dist-info/LICENSE
pycvextract-0.0.1.dist-info/METADATA
pycvextract-0.0.1.dist-info/WHEEL
pycvextract-0.0.1.dist-info/top_level.txt
pycvextract-0.0.1.dist-info/RECORD
